libMecapack/__init__.py
libMecapack/libCfg.py
libMecapack/libLog.py
libMecapack/libMail.py
libMecapack/libSql.py
libMecapack/libTool.py
libMecapack/libWebServices.py
libmecapack_light-1.1.0.dist-info/LICENSE
libmecapack_light-1.1.0.dist-info/WHEEL
libmecapack_light-1.1.0.dist-info/METADATA
libmecapack_light-1.1.0.dist-info/RECORD
