Metadata-Version: 2.1
Name: libMecapack_light
Version: 1.1.0
Summary: Library for MECAPACK python system
Author-email: Informatique Mecapack <informatique@mecapack.com>
Requires-Python: >=3.7
Classifier: License :: OSI Approved :: MIT License
Requires-Dist: arrow==1.2.3
Requires-Dist: pypyodbc==1.3.6
Requires-Dist: requests==2.28.1
Requires-Dist: suds==1.1.2
Requires-Dist: sortedcontainers==2.4.0
Requires-Dist: xmltodict==0.13.0
